selectq/__init__.py
selectq/browsers.py
selectq/interactions.py
selectq/predicates.py
selectq/selectq.py
selectq/shortcuts.py
selectq/gadgets/selectq.css
selectq/gadgets/selectq.js
selectq-0.0.7.data/data/LICENSE
selectq-0.0.7.dist-info/LICENSE
selectq-0.0.7.dist-info/METADATA
selectq-0.0.7.dist-info/WHEEL
selectq-0.0.7.dist-info/top_level.txt
selectq-0.0.7.dist-info/RECORD
