Metadata-Version: 2.1
Name: selectq
Version: 0.0.7
Summary: Non cryptic XML/HTML parsing
Home-page: https://github.com/SelectQuery/sQ
Author: Di Paola Martin
Author-email: use-github-issues@example.com
License: GNU GPLv3
Keywords: xml xpath,html
Platform: UNKNOWN
Classifier: Development Status :: 3 - Alpha
Classifier: Intended Audience :: Developers
Classifier: Topic :: Text Processing :: Markup :: XML
Classifier: Topic :: Text Processing :: Markup :: HTML
Classifier: License :: OSI Approved :: GNU General Public License v3 (GPLv3)
Classifier: Programming Language :: Python :: 3.4
Classifier: Programming Language :: Python :: 3.5
Classifier: Programming Language :: Python :: 3.6
Classifier: Programming Language :: Python :: 3.7
Classifier: Programming Language :: Python :: 3.8
Classifier: Programming Language :: Python :: 3.9
Requires-Python: >=3.5
Requires-Dist: lxml
Requires-Dist: requests
Requires-Dist: selenium
